qprocess/__init__.py
qprocess/gaussian.py
qprocess/mrcc.py
qprocess-0.1.0.dist-info/LICENCE
qprocess-0.1.0.dist-info/METADATA
qprocess-0.1.0.dist-info/WHEEL
qprocess-0.1.0.dist-info/top_level.txt
qprocess-0.1.0.dist-info/RECORD
