Metadata-Version: 2.1
Name: qprocess
Version: 0.1.0
Summary: A Python library for processing Quantum Chemical program output files
Home-page: https://github.com/fehergandalf/Gaussian.git
Author: Bogdan Virag
Author-email: viragbogdan@edu.bme.hu
Classifier: Programming Language :: Python :: 3
Classifier: License :: OSI Approved :: MIT License
Classifier: Operating System :: OS Independent
Requires-Python: >=3.9
License-File: LICENCE
Requires-Dist: pandas
Requires-Dist: numpy
